download_files/__init__.py
download_files/main.py
download_files/py.typed
download_files-0.1.0.dist-info/METADATA
download_files-0.1.0.dist-info/WHEEL
download_files-0.1.0.dist-info/entry_points.txt
download_files-0.1.0.dist-info/licenses/LICENSE.md
download_files-0.1.0.dist-info/RECORD
