Metadata-Version: 2.4
Name: download-files
Version: 0.1.0
Summary: Recursively download files from a web page, with specified extensions, listed in <a> elements. The list of files can be reviewed first. 
Project-URL: Repository, https://github.com/JamesParrott/download_files
Project-URL: Issues, https://github.com/JamesParrott/download_files/issues
Author-email: James Parrott <james.parrott@proton.me>
License: 
License-File: LICENSE.md
Requires-Python: >=3.11
Requires-Dist: beautifulsoup4
Requires-Dist: httpx
Requires-Dist: rich
Requires-Dist: typer
